[
  {
    "ID": "001",
    "Name": "节目一",
    "Describe": "节目一",
    "Author": "root",
    "Status": "1",
    "Share": "checked",
    "Time": "2017.07.25 13:25:36"
  },
  {
    "ID": "002",
    "Name": "节目二",
    "Describe": "节目二",
    "Author": "root",
    "Status": "0",
    "Share": "checked",
    "Time": "2017.07.25 13:25:36"
  },
  {
    "ID": "003",
    "Name": "节目三",
    "Describe": "节目三",
    "Author": "root",
    "Status": "1",
    "Share": "",
    "Time": "2017.07.25 13:25:36"
  },
  {
    "ID": "004",
    "Name": "节目四",
    "Describe": "节目四",
    "Author": "root",
    "Status": "0",
    "Share": "checked",
    "Time": "2017.07.25 13:25:36"
  },
  {
    "ID": "005",
    "Name": "节目五",
    "Describe": "节目五",
    "Author": "root",
    "Status": "1",
    "Share": "",
    "Time": "2017.07.25 13:25:36"
  },
  {
    "ID": "006",
    "Name": "节目六",
    "Describe": "节目六",
    "Author": "root",
    "Status": "0",
    "Share": "checked",
    "Time": "2017.07.25 13:25:36"
  }
]